Workbook

Sheet Inputs
A1: Input | B1: CNY mn / % | C1: Source
A2: revenue_2024 | B2: 285981.23 | C2: Annual report p10
A3: revenue_2023_adjusted | B3: 274204.52 | C3: Annual report p10
A4: revenue_2023_original | B4: 261427.78 | C4: Annual report p10
A5: parent_2024 | B5: 18741.12 | C5: Annual report p10
A6: parent_2023 | B6: 16596.615 | C6: Annual report p10
A7: CFO_2024 | B7: 26543.082 | C7: Annual report p10
A8: CFO_2023_adjusted | B8: 26535.781 | C8: Annual report p10
A9: CFO_2023_original | B9: 25262.376 | C9: Annual report p10
A10: warranty_reclass | B10: 8328.0875 | C10: Annual report p94
A11: ROE_2024 | B11: 17.7 | C11: Annual report p11
A12: ROE_2023_adjusted | B12: 17.24 | C12: Annual report p11
A13: ROE_2023_original | B13: 16.85 | C13: Annual report p11

Sheet Calculations
A1: Metric | B1: Basis | C1: 2024 | D1: 2023 comparator | E1: Formula result (%) | F1: Rule
A2: Revenue growth | B2: Original | C2: =Inputs!B2 | D2: =Inputs!B4 | E2: =C2/D2*100-100 | F2: (2024/2023-1)
A3: Revenue growth | B3: Adjusted | C3: =Inputs!B2 | D3: =Inputs!B3 | E3: =C3/D3*100-100 | F3: (2024/2023-1)
A4: Parent profit growth | B4: Both | C4: =Inputs!B5 | D4: =Inputs!B6 | E4: =C4/D4*100-100 | F4: same prior-year parent profit
A5: CFO growth | B5: Original | C5: =Inputs!B7 | D5: =Inputs!B9 | E5: =C5/D5*100-100 | F5: (2024/2023-1)
A6: CFO growth | B6: Adjusted | C6: =Inputs!B7 | D6: =Inputs!B8 | E6: =C6/D6*100-100 | F6: (2024/2023-1)
A7: 2023 parent net margin | B7: Original | C7: =Inputs!B6 | D7: =Inputs!B4 | E7: =C7/D7*100 | F7: parent profit/revenue
A8: 2023 parent net margin | B8: Adjusted | C8: =Inputs!B6 | D8: =Inputs!B3 | E8: =C8/D8*100 | F8: parent profit/revenue
A9: 2024 parent net margin | B9: Current | C9: =Inputs!B5 | D9: =Inputs!B2 | E9: =C9/D9*100 | F9: parent profit/revenue
A10: Warranty reclass pp | B10: policy only | C10: =Inputs!B10 | D10: =Inputs!B3 | E10: =C10/D10*100 | F10: Reclass / adjusted 2023 revenue; gross margin and selling expense rate effects opposite
